<?xml version = '1.0' encoding = 'UTF-8'?>
<FKIndexAssociation class="oracle.dbtools.crest.model.design.relational.FKIndexAssociation" directorySegmentName="seg_7" id="2715F47F-B4D7-F1B0-0B22-AA649EE438E8" containerWithKeyObject="5F9906E2-BB72-B8D9-10BA-CB0E936201C1" localFKIndex="2782DC0E-6DE6-3216-D295-0C4BE5B13375" name="FK_SERVICE_ADDRESS_LINE_OF_BU1">
<sourceConnName>SOLO_Prod</sourceConnName>
<sourceObjSchema>CHTR</sourceObjSchema>
<sourceObjName>FK_SERVICE_ADDRESS_LINE_OF_BU1</sourceObjName>
<createdBy>jandrews1</createdBy>
<createdTime>2015-08-11 13:21:16 UTC</createdTime>
<ownerDesignName>SOLO_DECEMBER_RE</ownerDesignName>
<deleteRule>NO ACTION</deleteRule>
<referredTableID>A8FA734A-3EBF-A89C-152F-ECDA4C31C3C0</referredTableID>
<keyObject>79FBAB83-C5F6-6142-5896-7AE358FBCDEB</keyObject>
<referredKeyID>79FBAB83-C5F6-6142-5896-7AE358FBCDEB</referredKeyID>
<mandatory>false</mandatory>
<transferable>true</transferable>
<rely>false</rely>
<columnDependencyConstraintGenerateInDDL>true</columnDependencyConstraintGenerateInDDL>
</FKIndexAssociation>