<?xml version = '1.0' encoding = 'UTF-8'?>
<FKIndexAssociation class="oracle.dbtools.crest.model.design.relational.FKIndexAssociation" directorySegmentName="seg_3" id="F29A6295-BD27-ACE6-8D74-9C9722185AE4" containerWithKeyObject="AB6BB896-9E61-1418-F75B-4AB8C5CB89E2" localFKIndex="5943BEC7-EABF-89B0-02D7-A123BB08D266" name="FK_EVENT_RELATED1">
<sourceConnName>SOLO_Prod</sourceConnName>
<sourceObjSchema>CHTR</sourceObjSchema>
<sourceObjName>FK_EVENT_RELATED1</sourceObjName>
<createdBy>jandrews1</createdBy>
<createdTime>2015-08-11 13:21:16 UTC</createdTime>
<ownerDesignName>SOLO_RE</ownerDesignName>
<deleteRule>NO ACTION</deleteRule>
<referredTableID>1B379F6D-5320-AC44-063E-94125B63609D</referredTableID>
<keyObject>FDCAA959-BD9A-2F56-0A86-8238501F4AD9</keyObject>
<referredKeyID>FDCAA959-BD9A-2F56-0A86-8238501F4AD9</referredKeyID>
<mandatory>true</mandatory>
<transferable>true</transferable>
<rely>false</rely>
<columnDependencyConstraintGenerateInDDL>true</columnDependencyConstraintGenerateInDDL>
</FKIndexAssociation>