<?xml version = '1.0' encoding = 'UTF-8'?>
<Relation class="oracle.dbtools.crest.model.design.logical.Relation" name="FK_TERRITORY1" directorySegmentName="seg_8" id="34B1470A-B319-162B-16C3-74BE2113116B">
<createdBy>jandrews1</createdBy>
<createdTime>2015-12-17 14:33:32 UTC</createdTime>
<generatorID>F41C7D9F-12D6-8627-0BC8-9F7A29CC4D49</generatorID>
<ownerDesignName>SOLO_DECEMBER_RE</ownerDesignName>
<engineerTo>
<item key="F751E03D-C8A7-4CF2-7EA7-CC30B209F748" value="true"/>
</engineerTo>
<sourcePk>4B995B9A-90A6-8848-1EE7-15C1588A513E</sourcePk>
<identifying>false</identifying>
<optionalSource>true</optionalSource>
<optionalTarget>false</optionalTarget>
<sourceCardinality>1</sourceCardinality>
<sourceEntity>E1771593-D294-CA61-8E14-0A9560E514D8</sourceEntity>
<targetCardinalityString>*</targetCardinalityString>
<targetEntity>7D78D8F4-440F-AD37-BA2E-48AC62736897</targetEntity>
<transferable>true</transferable>
<deleteRule>NO ACTION</deleteRule>
</Relation>