<?xml version = '1.0' encoding = 'UTF-8'?>
<Relation class="oracle.dbtools.crest.model.design.logical.Relation" name="FK_SPECIAL_REQUEST_STATUS2" directorySegmentName="seg_8" id="60F903A8-ACAB-133E-D840-D879DBD2B6DC">
<createdBy>jandrews1</createdBy>
<createdTime>2015-12-17 14:33:32 UTC</createdTime>
<generatorID>151D6CF4-A77F-0B1C-37CC-07EB1002ECF6</generatorID>
<ownerDesignName>SOLO_DECEMBER_RE</ownerDesignName>
<engineerTo>
<item key="F751E03D-C8A7-4CF2-7EA7-CC30B209F748" value="true"/>
</engineerTo>
<sourcePk>E6442B0A-E1E4-18AB-90DD-E597AC823F0A</sourcePk>
<dominantRole>87C528DC-6F30-BC36-9730-93236A16DC97</dominantRole>
<identifying>true</identifying>
<optionalSource>true</optionalSource>
<optionalTarget>false</optionalTarget>
<sourceCardinality>1</sourceCardinality>
<sourceEntity>87C528DC-6F30-BC36-9730-93236A16DC97</sourceEntity>
<targetCardinalityString>1</targetCardinalityString>
<targetEntity>5065CAE7-EDB7-B22C-D3F4-C891D84C4E9A</targetEntity>
<transferable>true</transferable>
<deleteRule>NO ACTION</deleteRule>
</Relation>