<?xml version = '1.0' encoding = 'UTF-8'?>
<TableProxyOraclev11g class="oracle.dbtools.crest.model.design.storage.oracle.v11g.TableProxyOraclev11g" name="T_SETTOP_BOX_ACCESS" directorySegmentName="seg_2" id="65214B3E-A36A-A38B-C646-4B55068228DB">
<createdBy>jandrews1</createdBy>
<createdTime>2015-08-11 13:07:43 UTC</createdTime>
<ownerDesignName>SOLO_DECEMBER_RE</ownerDesignName>
<schemaObject>FA693F2C-EF1B-3E65-88D8-7194D19EDCEE</schemaObject>
<logging>YES</logging>
<partitionedRowMovement>DISABLE</partitionedRowMovement>
<segment>7826BD17-4E2B-E228-F413-C9C5FB350CFB</segment>
<tableSpace>13A0D6EE-4ACF-AC9E-C994-1F7F5897441B</tableSpace>
<temporaryChanged>false</temporaryChanged>
<accessDriverType>oracle_loader</accessDriverType>
<rejectLimit></rejectLimit>
<columnProxies itemClass="oracle.dbtools.crest.model.design.storage.oracle.v12c.ColumnProxyOraclev12c">
<ColumnProxy name="CREATED_BY" id="14019E6B-6796-EBBA-0044-BDAC2C6CE700">
<createdBy>jandrews1</createdBy>
<createdTime>2015-08-11 13:09:43 UTC</createdTime>
<ownerDesignName>SOLO_DECEMBER_RE</ownerDesignName>
</ColumnProxy>
<ColumnProxy name="EQUIP_PROD_INST_ID" id="3461EF90-A7F0-B8DF-9307-D157888FBBA8">
<createdBy>jandrews1</createdBy>
<createdTime>2015-08-11 13:09:43 UTC</createdTime>
<ownerDesignName>SOLO_DECEMBER_RE</ownerDesignName>
</ColumnProxy>
<ColumnProxy name="SETTOP_BOX_MAC_ADDRESS_VAL" id="396B2389-BE93-D09D-34CB-41D65FFFA4D0">
<createdBy>jandrews1</createdBy>
<createdTime>2015-08-11 13:09:42 UTC</createdTime>
<ownerDesignName>SOLO_DECEMBER_RE</ownerDesignName>
</ColumnProxy>
<ColumnProxy name="MODIFIED_BY" id="3C83D43E-30A0-5B04-9726-EEC551604BC0">
<createdBy>jandrews1</createdBy>
<createdTime>2015-08-11 13:09:43 UTC</createdTime>
<ownerDesignName>SOLO_DECEMBER_RE</ownerDesignName>
</ColumnProxy>
<ColumnProxy name="RECORD_STAT" id="412170B8-5AA9-D859-31E8-5595C832073F">
<createdBy>jandrews1</createdBy>
<createdTime>2015-08-11 13:09:43 UTC</createdTime>
<ownerDesignName>SOLO_DECEMBER_RE</ownerDesignName>
</ColumnProxy>
<ColumnProxy name="SETTOP_BOX_ID" id="5C39A6AE-372A-8DCA-B882-A123C57C0806">
<createdBy>jandrews1</createdBy>
<createdTime>2015-08-11 13:09:42 UTC</createdTime>
<ownerDesignName>SOLO_DECEMBER_RE</ownerDesignName>
</ColumnProxy>
<ColumnProxy name="MODIFIED_DTTM" id="6A7A3EF0-DBF2-2FD0-BBA2-D4C5B1CDFA07">
<createdBy>jandrews1</createdBy>
<createdTime>2015-08-11 13:09:43 UTC</createdTime>
<ownerDesignName>SOLO_DECEMBER_RE</ownerDesignName>
</ColumnProxy>
<ColumnProxy name="CREATED_DTTM" id="8FA8DDD6-E1E0-6DF4-F2A1-43734B986886">
<createdBy>jandrews1</createdBy>
<createdTime>2015-08-11 13:09:43 UTC</createdTime>
<ownerDesignName>SOLO_DECEMBER_RE</ownerDesignName>
</ColumnProxy>
</columnProxies>
<indexProxies>
<IndexProxy class="oracle.dbtools.crest.model.design.storage.oracle.v10g.IndexProxyOraclev10g" name="PK_SETTOP_BOX_ACCESS" id="89559381-16A1-CF34-816E-4A8F544AC484">
<createdBy>jandrews1</createdBy>
<createdTime>2015-08-11 13:10:45 UTC</createdTime>
<ownerDesignName>SOLO_DECEMBER_RE</ownerDesignName>
<schemaObject>FA693F2C-EF1B-3E65-88D8-7194D19EDCEE</schemaObject>
<segment>C57E1CB0-FBCE-D3CE-0DA8-CAEB451A8B7F</segment>
<tableSpace>51799F23-4FFD-4DE3-74FE-AAC19AE85DC0</tableSpace>
</IndexProxy>
<IndexProxy class="oracle.dbtools.crest.model.design.storage.oracle.v10g.IndexProxyOraclev10g" name="IDX_SETTOP_BOX_ACCESS1" id="A3507899-7063-893C-4200-655659587CBC">
<createdBy>jandrews1</createdBy>
<createdTime>2015-08-11 13:10:45 UTC</createdTime>
<ownerDesignName>SOLO_DECEMBER_RE</ownerDesignName>
<schemaObject>FA693F2C-EF1B-3E65-88D8-7194D19EDCEE</schemaObject>
<segment>C57E1CB0-FBCE-D3CE-0DA8-CAEB451A8B7F</segment>
<tableSpace>51799F23-4FFD-4DE3-74FE-AAC19AE85DC0</tableSpace>
</IndexProxy>
</indexProxies>
<foreignKeys>
<ForeignKey class="oracle.dbtools.crest.model.design.storage.oracle.v10g.FKProxyOraclev10g" name="FK_SETTOP_BOX_ACCESS2" id="5735FC87-DB33-5F5C-E6A6-4BF378BDEAB4">
<createdBy>jandrews1</createdBy>
<createdTime>2015-08-11 13:21:16 UTC</createdTime>
<ownerDesignName>SOLO_DECEMBER_RE</ownerDesignName>
</ForeignKey>
<ForeignKey class="oracle.dbtools.crest.model.design.storage.oracle.v10g.FKProxyOraclev10g" name="FK_SETTOP_BOX_ACCESS1" id="87E90766-3620-A6FC-9D86-155E376165DF">
<createdBy>jandrews1</createdBy>
<createdTime>2015-08-11 13:21:16 UTC</createdTime>
<ownerDesignName>SOLO_DECEMBER_RE</ownerDesignName>
</ForeignKey>
</foreignKeys>
<primaryKeys>
<PrimaryKey class="oracle.dbtools.crest.model.design.storage.oracle.v10g.PKProxyOraclev10g" name="PK_SETTOP_BOX_ACCESS" id="721094C7-8562-6104-EBA7-23D3119669DB">
<createdBy>jandrews1</createdBy>
<createdTime>2015-08-11 13:12:44 UTC</createdTime>
<ownerDesignName>SOLO_DECEMBER_RE</ownerDesignName>
<segment>C57E1CB0-FBCE-D3CE-0DA8-CAEB451A8B7F</segment>
<tableSpace>51799F23-4FFD-4DE3-74FE-AAC19AE85DC0</tableSpace>
<existingIndex>89559381-16A1-CF34-816E-4A8F544AC484</existingIndex>
<indexSegment>C57E1CB0-FBCE-D3CE-0DA8-CAEB451A8B7F</indexSegment>
<indexSort>SORTED</indexSort>
<usingIndex>BY INDEX NAME</usingIndex>
</PrimaryKey>
</primaryKeys>
</TableProxyOraclev11g>