<?xml version = '1.0' encoding = 'UTF-8'?>
<Relation class="oracle.dbtools.crest.model.design.logical.Relation" name="FK_ACCOUNTING_SYSTEM3" directorySegmentName="seg_0" id="968B0606-D431-E1B4-FA18-138AE427B6B5">
<createdBy>jandrews1</createdBy>
<createdTime>2015-12-17 14:33:29 UTC</createdTime>
<generatorID>9E84F045-7C1D-3DA3-1A3D-5CD22CECD9D1</generatorID>
<ownerDesignName>SOLO_DECEMBER_RE</ownerDesignName>
<engineerTo>
<item key="F751E03D-C8A7-4CF2-7EA7-CC30B209F748" value="true"/>
</engineerTo>
<sourcePk>8604CC30-046A-8FF5-D445-6C86C5C29501</sourcePk>
<identifying>false</identifying>
<optionalSource>true</optionalSource>
<optionalTarget>true</optionalTarget>
<sourceCardinality>1</sourceCardinality>
<sourceEntity>139897A4-A61D-5522-FD3E-E41D626FD122</sourceEntity>
<targetCardinalityString>*</targetCardinalityString>
<targetEntity>BE471F6A-6D28-5707-B2B1-5C9DCCAB55F1</targetEntity>
<transferable>true</transferable>
<deleteRule>NO ACTION</deleteRule>
</Relation>