<?xml version = '1.0' encoding = 'UTF-8'?>
<Relation class="oracle.dbtools.crest.model.design.logical.Relation" name="FK_ACCOUNT_STATUS_CD1" directorySegmentName="seg_0" id="B12B576B-7FDF-F81A-2AE1-2C8E078364DB">
<createdBy>jandrews1</createdBy>
<createdTime>2015-12-17 14:33:29 UTC</createdTime>
<generatorID>560D5129-C447-E22F-8BFE-40E72C14B925</generatorID>
<ownerDesignName>SOLO_DECEMBER_RE</ownerDesignName>
<engineerTo>
<item key="F751E03D-C8A7-4CF2-7EA7-CC30B209F748" value="true"/>
</engineerTo>
<sourcePk>7B844266-C90D-777B-68D2-CC98443DCD1F</sourcePk>
<identifying>true</identifying>
<optionalSource>true</optionalSource>
<optionalTarget>false</optionalTarget>
<sourceCardinality>1</sourceCardinality>
<sourceEntity>F46613BF-2719-3B62-15CA-1F75F3E7161F</sourceEntity>
<targetCardinalityString>*</targetCardinalityString>
<targetEntity>D4BF4369-DD8E-20C5-2015-7213AE60AA63</targetEntity>
<transferable>true</transferable>
<deleteRule>NO ACTION</deleteRule>
</Relation>