<?xml version = '1.0' encoding = 'UTF-8'?>
<FKIndexAssociation class="oracle.dbtools.crest.model.design.relational.FKIndexAssociation" directorySegmentName="seg_1" id="E15ED8C7-3944-7E1F-8112-EEFB5A3BF584" containerWithKeyObject="2772CA2A-A4D7-5FAE-0F99-339FD7B7FB4D" localFKIndex="D0B4939A-389F-8A96-A636-0C753A22A52D" name="FK_AGREEMENT_ACCESS_METHOD1">
<sourceConnName>SOLO_Prod</sourceConnName>
<sourceObjSchema>CHTR</sourceObjSchema>
<sourceObjName>FK_AGREEMENT_ACCESS_METHOD1</sourceObjName>
<createdBy>jandrews1</createdBy>
<createdTime>2015-08-11 13:21:15 UTC</createdTime>
<ownerDesignName>SOLO_RE</ownerDesignName>
<deleteRule>NO ACTION</deleteRule>
<referredTableID>C28E959E-21F5-BB7A-E37D-E383553AEE4E</referredTableID>
<keyObject>B82B9833-37F4-0E5E-1B4A-BB214DC18833</keyObject>
<referredKeyID>B82B9833-37F4-0E5E-1B4A-BB214DC18833</referredKeyID>
<mandatory>true</mandatory>
<transferable>true</transferable>
<rely>false</rely>
<columnDependencyConstraintGenerateInDDL>true</columnDependencyConstraintGenerateInDDL>
</FKIndexAssociation>