<?xml version = '1.0' encoding = 'UTF-8'?>
<Relation class="oracle.dbtools.crest.model.design.logical.Relation" name="Offer Component FK" directorySegmentName="seg_1" id="7035CED6-E419-9281-228F-87EF803D4FB7">
<createdBy>jandrews</createdBy>
<createdTime>2016-01-18 17:50:03 UTC</createdTime>
<ownerDesignName>GODS</ownerDesignName>
<engineerTo>
<item key="2C9795F5-6744-BF02-0E89-A6A9E7D0E0DB" value="true"/>
</engineerTo>
<sourcePk>F3495D54-9194-B5B4-8E72-EF373876B734</sourcePk>
<identifying>false</identifying>
<optionalSource>true</optionalSource>
<optionalTarget>false</optionalTarget>
<sourceCardinality>1</sourceCardinality>
<sourceEntity>7FF90BD7-D4A4-DD69-1E6F-E76EF7FD4D5C</sourceEntity>
<targetCardinalityString>*</targetCardinalityString>
<targetEntity>FFD9FED9-9C7F-4084-A616-90777AC2ECAD</targetEntity>
<transferable>true</transferable>
<deleteRule>NO ACTION</deleteRule>
</Relation>