<?xml version = '1.0' encoding = 'UTF-8'?>
<FKIndexAssociation class="oracle.dbtools.crest.model.design.relational.FKIndexAssociation" directorySegmentName="seg_2" id="8CC74AC9-999D-F279-3734-AF5D17A89D3D" containerWithKeyObject="4439800D-1231-6B0B-3A58-6EF41BFDD51C" localFKIndex="9E86CA25-D336-A41E-EF0D-3EC0FA6E4749" name="FK_CONTENT_LOCATOR1">
<sourceConnName>SOLO_Prod</sourceConnName>
<sourceObjSchema>CHTR</sourceObjSchema>
<sourceObjName>FK_CONTENT_LOCATOR1</sourceObjName>
<createdBy>jandrews1</createdBy>
<createdTime>2015-08-11 13:21:16 UTC</createdTime>
<ownerDesignName>SOLO_RE</ownerDesignName>
<deleteRule>NO ACTION</deleteRule>
<referredTableID>82CB15DD-11E4-A112-575C-63E08752CB59</referredTableID>
<keyObject>B16FFD22-E332-BFC5-59FE-E52162D641B5</keyObject>
<referredKeyID>B16FFD22-E332-BFC5-59FE-E52162D641B5</referredKeyID>
<mandatory>false</mandatory>
<transferable>true</transferable>
<rely>false</rely>
<columnDependencyConstraintGenerateInDDL>true</columnDependencyConstraintGenerateInDDL>
</FKIndexAssociation>