<?xml version = '1.0' encoding = 'UTF-8'?>
<Relation class="oracle.dbtools.crest.model.design.logical.Relation" name="FK_ASSOCIATE_LOGON2" directorySegmentName="seg_1" id="5F79C534-0869-6AAB-63E5-FFA22E9FC012">
<createdBy>jandrews1</createdBy>
<createdTime>2015-12-17 14:33:29 UTC</createdTime>
<generatorID>EF7E24E7-3E8C-33FF-DF0B-A208140B7A60</generatorID>
<ownerDesignName>SOLO_DECEMBER_RE</ownerDesignName>
<engineerTo>
<item key="F751E03D-C8A7-4CF2-7EA7-CC30B209F748" value="true"/>
</engineerTo>
<sourcePk>DAFC90D0-5D4E-0586-AEC2-99B660BC65B5</sourcePk>
<identifying>true</identifying>
<optionalSource>true</optionalSource>
<optionalTarget>false</optionalTarget>
<sourceCardinality>1</sourceCardinality>
<sourceEntity>0BEC8946-DDBE-CF34-CFB5-4B28EDEE72FF</sourceEntity>
<targetCardinalityString>*</targetCardinalityString>
<targetEntity>3CBEE006-491E-1983-CE4B-9C83CE21EC4F</targetEntity>
<transferable>true</transferable>
<deleteRule>NO ACTION</deleteRule>
</Relation>