<?xml version = '1.0' encoding = 'UTF-8'?>
<Relation class="oracle.dbtools.crest.model.design.logical.Relation" name="FK_BILLING_PROD_INST5" directorySegmentName="seg_1" id="CB822726-741D-AFAB-AA2E-35A6B855AA64">
<createdBy>jandrews1</createdBy>
<createdTime>2015-12-17 14:33:29 UTC</createdTime>
<generatorID>319FEBA3-3E88-ED91-7A12-EB08CAA30712</generatorID>
<ownerDesignName>SOLO_DECEMBER_RE</ownerDesignName>
<engineerTo>
<item key="F751E03D-C8A7-4CF2-7EA7-CC30B209F748" value="true"/>
</engineerTo>
<sourcePk>C301BC12-5A3C-D145-4F6D-2FDE008C5C5D</sourcePk>
<identifying>false</identifying>
<optionalSource>true</optionalSource>
<optionalTarget>true</optionalTarget>
<sourceCardinality>1</sourceCardinality>
<sourceEntity>B818B5E2-2513-EB91-81FE-A0B20FEEB4D4</sourceEntity>
<targetCardinalityString>*</targetCardinalityString>
<targetEntity>9AC50FD4-227F-1D2F-46FC-16D2E9EE4CE6</targetEntity>
<transferable>true</transferable>
<deleteRule>NO ACTION</deleteRule>
</Relation>