<?xml version = '1.0' encoding = 'UTF-8'?>
<Relation class="oracle.dbtools.crest.model.design.logical.Relation" name="FK_PO_BOX_ADDR5" directorySegmentName="seg_5" id="59874B97-D6EF-646D-9C71-B660423AB2D2">
<createdBy>jandrews1</createdBy>
<createdTime>2015-12-17 14:33:30 UTC</createdTime>
<generatorID>493D0625-F110-1A2B-CFC6-3E56A0788658</generatorID>
<ownerDesignName>SOLO_DECEMBER_RE</ownerDesignName>
<engineerTo>
<item key="F751E03D-C8A7-4CF2-7EA7-CC30B209F748" value="true"/>
</engineerTo>
<sourcePk>F743C832-5A10-0F70-6B49-7B5F579ED477</sourcePk>
<identifying>false</identifying>
<optionalSource>true</optionalSource>
<optionalTarget>true</optionalTarget>
<sourceCardinality>1</sourceCardinality>
<sourceEntity>7D78D8F4-440F-AD37-BA2E-48AC62736897</sourceEntity>
<targetCardinalityString>*</targetCardinalityString>
<targetEntity>5B5F0E70-1A85-15B6-76FD-1C22B7B8D284</targetEntity>
<transferable>true</transferable>
<deleteRule>NO ACTION</deleteRule>
</Relation>