<?xml version = '1.0' encoding = 'UTF-8'?>
<Relation class="oracle.dbtools.crest.model.design.logical.Relation" name="FK_ORGANIZATION_HEIRARCHY1" directorySegmentName="seg_5" id="F1D3AB98-7DA5-159A-D831-B5A93BF60C94">
<createdBy>jandrews1</createdBy>
<createdTime>2015-12-17 14:33:30 UTC</createdTime>
<generatorID>85B4EE75-A699-2B6A-E3FC-A456EFD96587</generatorID>
<ownerDesignName>SOLO_DECEMBER_RE</ownerDesignName>
<engineerTo>
<item key="F751E03D-C8A7-4CF2-7EA7-CC30B209F748" value="true"/>
</engineerTo>
<sourcePk>29374328-F0A5-76D0-9138-2BFAD283538D</sourcePk>
<identifying>false</identifying>
<optionalSource>true</optionalSource>
<optionalTarget>true</optionalTarget>
<sourceCardinality>1</sourceCardinality>
<sourceEntity>AD073F2D-FEFD-6937-FCBD-9940211DBDDF</sourceEntity>
<targetCardinalityString>*</targetCardinalityString>
<targetEntity>AC4BD78A-38B3-0548-D235-31732CC8723D</targetEntity>
<transferable>true</transferable>
<deleteRule>SET NULL</deleteRule>
</Relation>