<?xml version = '1.0' encoding = 'UTF-8'?>
<FKIndexAssociation class="oracle.dbtools.crest.model.design.relational.FKIndexAssociation" directorySegmentName="seg_4" id="76D0222E-B80C-A9B4-A523-9B7B43C588AA" containerWithKeyObject="9D519C57-2FD1-3229-AFA1-8E2D00FF947E" localFKIndex="B6A9437D-73F9-A2F8-522C-D114E2DC118D" name="FK_INTERNET_EMAIL_ADDRESS1">
<sourceConnName>SOLO_Prod</sourceConnName>
<sourceObjSchema>CHTR</sourceObjSchema>
<sourceObjName>FK_INTERNET_EMAIL_ADDRESS1</sourceObjName>
<createdBy>jandrews1</createdBy>
<createdTime>2015-08-11 13:21:16 UTC</createdTime>
<ownerDesignName>SOLO_RE</ownerDesignName>
<deleteRule>NO ACTION</deleteRule>
<referredTableID>C28E959E-21F5-BB7A-E37D-E383553AEE4E</referredTableID>
<keyObject>B82B9833-37F4-0E5E-1B4A-BB214DC18833</keyObject>
<referredKeyID>B82B9833-37F4-0E5E-1B4A-BB214DC18833</referredKeyID>
<mandatory>true</mandatory>
<transferable>true</transferable>
<rely>false</rely>
<columnDependencyConstraintGenerateInDDL>true</columnDependencyConstraintGenerateInDDL>
</FKIndexAssociation>