<?xml version = '1.0' encoding = 'UTF-8'?>
<FKIndexAssociation class="oracle.dbtools.crest.model.design.relational.FKIndexAssociation" directorySegmentName="seg_4" id="E6EE09CC-F70F-9351-009D-FD3E9FD94562" containerWithKeyObject="340EA3BF-EDF8-2D34-5429-01A978DCD351" localFKIndex="F6DC3D35-7675-251D-8E3D-8E9BC0F3920F" name="FK_LINEAR_SOURCE_MAP1">
<sourceConnName>SOLO_Prod</sourceConnName>
<sourceObjSchema>CHTR</sourceObjSchema>
<sourceObjName>FK_LINEAR_SOURCE_MAP1</sourceObjName>
<createdBy>jandrews1</createdBy>
<createdTime>2015-08-11 13:21:16 UTC</createdTime>
<ownerDesignName>SOLO_RE</ownerDesignName>
<deleteRule>NO ACTION</deleteRule>
<referredTableID>C2B1935A-BF50-B51C-279C-367772288970</referredTableID>
<keyObject>284A678D-AE6A-3AFA-CFC0-D8730F704541</keyObject>
<referredKeyID>284A678D-AE6A-3AFA-CFC0-D8730F704541</referredKeyID>
<mandatory>true</mandatory>
<transferable>true</transferable>
<rely>false</rely>
<columnDependencyConstraintGenerateInDDL>true</columnDependencyConstraintGenerateInDDL>
</FKIndexAssociation>