<?xml version = '1.0' encoding = 'UTF-8'?>
<PackageOracle class="oracle.dbtools.crest.model.design.storage.oracle.PackageOracle" name="DA_PRODUCT_GROUP" directorySegmentName="seg_4" id="CBA6A36A-238F-E048-8CFF-9A4836EA86DB">
<sourceConnName>SOLO_Prod</sourceConnName>
<sourceObjSchema>CHTR</sourceObjSchema>
<sourceObjName>DA_PRODUCT_GROUP</sourceObjName>
<createdBy>jandrews1</createdBy>
<createdTime>2015-08-11 13:15:45 UTC</createdTime>
<ownerDesignName>SOLO_RE</ownerDesignName>
<owner>5AF9E3FC-7A76-C437-3E83-BF29D7EA2FC7</owner>
<source>CREATE OR REPLACE PACKAGE CHTR.DA_PRODUCT_GROUP&lt;br/&gt;/* Generated on 20-JAN-15 03.40.10.306271000 PM -06:00 */&lt;br/&gt;AS&lt;br/&gt; &lt;br/&gt;   PROCEDURE add (&lt;br/&gt;      process_rec IN pkg_logging.t_process_rec&lt;br/&gt;      ,product_group_cd IN VARCHAR2&lt;br/&gt;      ,product_group_start_dt IN DATE&lt;br/&gt;      ,product_group_end_dt IN DATE&lt;br/&gt;      ,product_group_desc IN VARCHAR2&lt;br/&gt;      ,audit_user IN VARCHAR2&lt;br/&gt;   );&lt;br/&gt; &lt;br/&gt;   PROCEDURE del (&lt;br/&gt;      process_rec IN pkg_logging.t_process_rec&lt;br/&gt;      ,product_group_cd IN VARCHAR2&lt;br/&gt;      ,audit_user IN VARCHAR2&lt;br/&gt;   );&lt;br/&gt; &lt;br/&gt;END da_product_group;</source>
<body class="oracle.dbtools.crest.model.design.storage.oracle.PackageBodyOracle" name="DA_PRODUCT_GROUP" id="CBA6A36A-238F-E048-8CFF-9A4836EA86DB">
<sourceConnName>SOLO_Prod</sourceConnName>
<sourceObjSchema>CHTR</sourceObjSchema>
<sourceObjName>DA_PRODUCT_GROUP</sourceObjName>
<createdBy>jandrews1</createdBy>
<createdTime>2015-08-11 13:15:46 UTC</createdTime>
<ownerDesignName>SOLO_RE</ownerDesignName>
<owner>5AF9E3FC-7A76-C437-3E83-BF29D7EA2FC7</owner>
<source>CREATE OR REPLACE PACKAGE BODY CHTR.DA_PRODUCT_GROUP&lt;br/&gt;/* Generated on 20-JAN-15 03.40.10.315664000 PM -06:00 */&lt;br/&gt;AS&lt;br/&gt; &lt;br/&gt;   PROCEDURE add (&lt;br/&gt;      process_rec IN pkg_logging.t_process_rec&lt;br/&gt;      ,product_group_cd IN VARCHAR2&lt;br/&gt;      ,product_group_start_dt IN DATE&lt;br/&gt;      ,product_group_end_dt IN DATE&lt;br/&gt;      ,product_group_desc IN VARCHAR2&lt;br/&gt;      ,audit_user IN VARCHAR2&lt;br/&gt;   )&lt;br/&gt;   IS&lt;br/&gt;   BEGIN&lt;br/&gt; &lt;br/&gt;      chtr.pkg_logging.log_debug (process_rec, &apos;begin da_product_group.add, parms=&apos; || product_group_cd || &apos;|&apos; || product_group_start_dt || &apos;|&apos; || product_group_end_dt || &apos;|&apos; || product_group_desc || &apos;|&apos; || audit_user || &apos;|&apos;);&lt;br/&gt;      INSERT INTO chtr.t_product_group a&lt;br/&gt;      (&lt;br/&gt;         a.product_group_cd&lt;br/&gt;         ,a.product_group_start_dt&lt;br/&gt;         ,a.product_group_end_dt&lt;br/&gt;         ,a.product_group_desc&lt;br/&gt;         ,a.record_stat&lt;br/&gt;         ,a.created_dttm&lt;br/&gt;         ,a.created_by&lt;br/&gt;         ,a.modified_dttm&lt;br/&gt;         ,a.modified_by&lt;br/&gt;      )&lt;br/&gt;      VALUES&lt;br/&gt;      (&lt;br/&gt;         add.product_group_cd&lt;br/&gt;         ,add.product_group_start_dt&lt;br/&gt;         ,add.product_group_end_dt&lt;br/&gt;         ,add.product_group_desc&lt;br/&gt;         ,&apos;A&apos;&lt;br/&gt;         ,SYSTIMESTAMP&lt;br/&gt;         ,add.audit_user&lt;br/&gt;         ,NULL&lt;br/&gt;         ,NULL&lt;br/&gt;      );&lt;br/&gt;      chtr.pkg_logging.log_debug (process_rec, &apos;end da_product_group.add&apos;);&lt;br/&gt; &lt;br/&gt;   END add;&lt;br/&gt; &lt;br/&gt;   PROCEDURE del (&lt;br/&gt;      process_rec IN pkg_logging.t_process_rec&lt;br/&gt;      ,product_group_cd IN VARCHAR2&lt;br/&gt;      ,audit_user IN VARCHAR2&lt;br/&gt;   )&lt;br/&gt;   IS&lt;br/&gt;   BEGIN&lt;br/&gt; &lt;br/&gt;      chtr.pkg_logging.log_debug (process_rec, &apos;begin da_product_group.del, parms=&apos; || product_group_cd || &apos;|&apos; || audit_user || &apos;|&apos;);&lt;br/&gt;      UPDATE chtr.t_product_group a&lt;br/&gt;      SET a.record_stat = &apos;D&apos;&lt;br/&gt;          ,a.modified_dttm = SYSTIMESTAMP&lt;br/&gt;          ,a.modified_by = del.audit_user&lt;br/&gt;      WHERE a.product_group_cd = del.product_group_cd&lt;br/&gt;      ;&lt;br/&gt;      chtr.pkg_logging.log_debug (process_rec, &apos;end da_product_group.del&apos;);&lt;br/&gt; &lt;br/&gt;   END del;&lt;br/&gt; &lt;br/&gt;END da_product_group;</source>
</body>
</PackageOracle>