<?xml version = '1.0' encoding = 'UTF-8'?>
<TableProxyOraclev11g class="oracle.dbtools.crest.model.design.storage.oracle.v11g.TableProxyOraclev11g" name="T_LOB_STATUS_CD" directorySegmentName="seg_2" id="F05633B3-8D08-3489-A06D-0CE3403F1A1B">
<createdBy>jandrews1</createdBy>
<createdTime>2015-12-14 16:27:59 UTC</createdTime>
<ownerDesignName>SOLO_PROD_RE</ownerDesignName>
<schemaObject>B5DA1D80-BC1F-DEEB-A262-CA58037BF88D</schemaObject>
<logging>YES</logging>
<partitionedRowMovement>DISABLE</partitionedRowMovement>
<segment>D7A040AF-41FC-B1B2-8956-0AB09A6C3779</segment>
<tableSpace>544A9975-5542-4D76-7D86-BABC95BC67F9</tableSpace>
<temporaryChanged>false</temporaryChanged>
<accessDriverType>oracle_loader</accessDriverType>
<rejectLimit></rejectLimit>
<columnProxies itemClass="oracle.dbtools.crest.model.design.storage.oracle.v12c.ColumnProxyOraclev12c">
<ColumnProxy name="MODIFIED_BY" id="21018879-9646-D300-F3D8-AA65B9C7F06F">
<createdBy>jandrews1</createdBy>
<createdTime>2015-12-14 16:28:36 UTC</createdTime>
<ownerDesignName>SOLO_PROD_RE</ownerDesignName>
</ColumnProxy>
<ColumnProxy name="CREATED_BY" id="36B2B4D9-1B65-6193-BF51-A4DBE89E28C7">
<createdBy>jandrews1</createdBy>
<createdTime>2015-12-14 16:28:35 UTC</createdTime>
<ownerDesignName>SOLO_PROD_RE</ownerDesignName>
</ColumnProxy>
<ColumnProxy name="LOB_STATUS_CD" id="55AA63D3-98D6-110D-CFC6-5D47682EC00E">
<createdBy>jandrews1</createdBy>
<createdTime>2015-12-14 16:28:35 UTC</createdTime>
<ownerDesignName>SOLO_PROD_RE</ownerDesignName>
</ColumnProxy>
<ColumnProxy name="MODIFIED_DTTM" id="6B7404AA-96F8-86B4-B301-5B20414A81F0">
<createdBy>jandrews1</createdBy>
<createdTime>2015-12-14 16:28:35 UTC</createdTime>
<ownerDesignName>SOLO_PROD_RE</ownerDesignName>
</ColumnProxy>
<ColumnProxy name="RECORD_STAT" id="7A28D0F8-8157-F976-37AC-4A23EE0A510B">
<createdBy>jandrews1</createdBy>
<createdTime>2015-12-14 16:28:35 UTC</createdTime>
<ownerDesignName>SOLO_PROD_RE</ownerDesignName>
</ColumnProxy>
<ColumnProxy name="LOB_STATUS_DESC" id="7E47342D-6750-0A77-D570-4F62D916548E">
<createdBy>jandrews1</createdBy>
<createdTime>2015-12-14 16:28:35 UTC</createdTime>
<ownerDesignName>SOLO_PROD_RE</ownerDesignName>
</ColumnProxy>
<ColumnProxy name="CREATED_DTTM" id="99CB9415-2F27-CD05-CF78-FB67881D3052">
<createdBy>jandrews1</createdBy>
<createdTime>2015-12-14 16:28:35 UTC</createdTime>
<ownerDesignName>SOLO_PROD_RE</ownerDesignName>
</ColumnProxy>
<ColumnProxy name="DATA_SOURCE_TYPE_CD" id="DD6145D5-DF78-0500-C3C4-C24602C30912">
<createdBy>jandrews1</createdBy>
<createdTime>2015-12-14 16:28:35 UTC</createdTime>
<ownerDesignName>SOLO_PROD_RE</ownerDesignName>
</ColumnProxy>
</columnProxies>
<indexProxies>
<IndexProxy class="oracle.dbtools.crest.model.design.storage.oracle.v10g.IndexProxyOraclev10g" name="PK_LOB_STATUS" id="40D4D06B-6F81-1394-904A-A7AC4D6B4A8F">
<createdBy>jandrews1</createdBy>
<createdTime>2015-12-14 16:29:26 UTC</createdTime>
<ownerDesignName>SOLO_PROD_RE</ownerDesignName>
<schemaObject>B5DA1D80-BC1F-DEEB-A262-CA58037BF88D</schemaObject>
<segment>5B2F1CD8-FA41-704C-A659-499E3FDD7D3A</segment>
<tableSpace>62BEF684-7708-E06C-239E-48713DCB04E5</tableSpace>
</IndexProxy>
</indexProxies>
<primaryKeys>
<PrimaryKey class="oracle.dbtools.crest.model.design.storage.oracle.v10g.PKProxyOraclev10g" name="PK_LOB_STATUS" id="E6C9C875-DBD8-F0B5-94C7-9AC7D227F741">
<createdBy>jandrews1</createdBy>
<createdTime>2015-12-14 16:30:02 UTC</createdTime>
<ownerDesignName>SOLO_PROD_RE</ownerDesignName>
<segment>5B2F1CD8-FA41-704C-A659-499E3FDD7D3A</segment>
<tableSpace>62BEF684-7708-E06C-239E-48713DCB04E5</tableSpace>
<existingIndex>40D4D06B-6F81-1394-904A-A7AC4D6B4A8F</existingIndex>
<indexSegment>5B2F1CD8-FA41-704C-A659-499E3FDD7D3A</indexSegment>
<indexSort>SORTED</indexSort>
<usingIndex>BY INDEX NAME</usingIndex>
</PrimaryKey>
</primaryKeys>
</TableProxyOraclev11g>