<?xml version = '1.0' encoding = 'UTF-8'?>
<TableProxyOraclev11g class="oracle.dbtools.crest.model.design.storage.oracle.v11g.TableProxyOraclev11g" name="T_MEC_ATTRIBUTE_VALUE" directorySegmentName="seg_0" id="A5D6C105-B20F-5FA3-7EF3-40456F778E0A">
<createdBy>jandrews1</createdBy>
<createdTime>2016-03-03 21:09:21 UTC</createdTime>
<ownerDesignName>SOLO_MEC_Tables_v1</ownerDesignName>
<schemaObject>E7FE513C-9018-FE2C-2B46-6C26966C9564</schemaObject>
<logging>YES</logging>
<partitionedRowMovement>DISABLE</partitionedRowMovement>
<segment>9DCA0A95-7D38-149B-5A7C-A4AB8FCE0B13</segment>
<tableSpace>0E884AB9-CB77-0A62-C14A-C790E5634C14</tableSpace>
<temporaryChanged>false</temporaryChanged>
<accessDriverType>oracle_loader</accessDriverType>
<rejectLimit></rejectLimit>
<columnProxies itemClass="oracle.dbtools.crest.model.design.storage.oracle.v12c.ColumnProxyOraclev12c">
<ColumnProxy name="PROPERTY_ID" id="0B5D6DE7-FD5E-8B9A-0B57-27F8EAE0F3BF">
<createdBy>jandrews1</createdBy>
<createdTime>2016-03-03 21:09:22 UTC</createdTime>
<ownerDesignName>SOLO_MEC_Tables_v1</ownerDesignName>
</ColumnProxy>
<ColumnProxy name="AP_ID" id="0DE78826-713A-505C-CE41-51E78E13CC7F">
<createdBy>jandrews1</createdBy>
<createdTime>2016-03-03 21:09:22 UTC</createdTime>
<ownerDesignName>SOLO_MEC_Tables_v1</ownerDesignName>
</ColumnProxy>
<ColumnProxy name="MODIFIED_BY" id="3134F963-4305-F786-939C-8B89E86EF9AF">
<createdBy>jandrews1</createdBy>
<createdTime>2016-03-03 21:09:22 UTC</createdTime>
<ownerDesignName>SOLO_MEC_Tables_v1</ownerDesignName>
</ColumnProxy>
<ColumnProxy name="VALUE_DATA_TYPE" id="3D0E1AB9-D897-A1D5-1907-9B0D733B3DE5">
<createdBy>jandrews1</createdBy>
<createdTime>2016-03-03 21:09:22 UTC</createdTime>
<ownerDesignName>SOLO_MEC_Tables_v1</ownerDesignName>
</ColumnProxy>
<ColumnProxy name="CID" id="3F91E472-4985-6A0E-8D92-23178FD0CD88">
<createdBy>jandrews1</createdBy>
<createdTime>2016-03-03 21:09:22 UTC</createdTime>
<ownerDesignName>SOLO_MEC_Tables_v1</ownerDesignName>
</ColumnProxy>
<ColumnProxy name="ATTRIBUTE_ACTION_CD" id="781F68FF-9FD6-D712-5845-9044286D1DB6">
<createdBy>jandrews1</createdBy>
<createdTime>2016-03-03 21:09:22 UTC</createdTime>
<ownerDesignName>SOLO_MEC_Tables_v1</ownerDesignName>
</ColumnProxy>
<ColumnProxy name="PROPERTY_VALUE" id="7F0E80B6-F463-4B7D-1D0C-567923F4F13D">
<createdBy>jandrews1</createdBy>
<createdTime>2016-03-03 21:09:22 UTC</createdTime>
<ownerDesignName>SOLO_MEC_Tables_v1</ownerDesignName>
</ColumnProxy>
<ColumnProxy name="CREATED_BY" id="956B6612-9948-0DDC-8D1F-0139210CD9C9">
<createdBy>jandrews1</createdBy>
<createdTime>2016-03-03 21:09:22 UTC</createdTime>
<ownerDesignName>SOLO_MEC_Tables_v1</ownerDesignName>
</ColumnProxy>
<ColumnProxy name="AP_VERSION_ID" id="B72E608E-BD6C-280A-B306-4AD2F6AAC928">
<createdBy>jandrews1</createdBy>
<createdTime>2016-03-03 21:09:22 UTC</createdTime>
<ownerDesignName>SOLO_MEC_Tables_v1</ownerDesignName>
</ColumnProxy>
<ColumnProxy name="CREATED_DTTM" id="B764B78A-2AC7-0449-8CAC-9C84E312F849">
<createdBy>jandrews1</createdBy>
<createdTime>2016-03-03 21:09:22 UTC</createdTime>
<ownerDesignName>SOLO_MEC_Tables_v1</ownerDesignName>
</ColumnProxy>
<ColumnProxy name="MODIFIED_DTTM" id="BBB3340A-2552-D8BC-50DC-EFF371E59C50">
<createdBy>jandrews1</createdBy>
<createdTime>2016-03-03 21:09:22 UTC</createdTime>
<ownerDesignName>SOLO_MEC_Tables_v1</ownerDesignName>
</ColumnProxy>
<ColumnProxy name="EFFECTIVE_DATE" id="C5B74FDC-ABE9-4137-FB22-067138D1C58E">
<createdBy>jandrews1</createdBy>
<createdTime>2016-03-03 21:09:22 UTC</createdTime>
<ownerDesignName>SOLO_MEC_Tables_v1</ownerDesignName>
</ColumnProxy>
<ColumnProxy name="END_DATE" id="C88E2C09-2A1D-42CC-91A6-B3626DC100A7">
<createdBy>jandrews1</createdBy>
<createdTime>2016-03-03 21:09:22 UTC</createdTime>
<ownerDesignName>SOLO_MEC_Tables_v1</ownerDesignName>
</ColumnProxy>
<ColumnProxy name="RECORD_STAT" id="D228E79F-58F7-6915-341B-94F364F89AE6">
<createdBy>jandrews1</createdBy>
<createdTime>2016-03-03 21:09:22 UTC</createdTime>
<ownerDesignName>SOLO_MEC_Tables_v1</ownerDesignName>
</ColumnProxy>
<ColumnProxy name="PCVERSION_ID" id="DF81E66B-F497-B161-E711-3FE6A0C0FC3E">
<createdBy>jandrews1</createdBy>
<createdTime>2016-03-03 21:09:22 UTC</createdTime>
<ownerDesignName>SOLO_MEC_Tables_v1</ownerDesignName>
</ColumnProxy>
</columnProxies>
<indexProxies>
<IndexProxy class="oracle.dbtools.crest.model.design.storage.oracle.v10g.IndexProxyOraclev10g" name="PK_MEC_ATTRIBUTE_VALUE" id="9AF008A8-8D02-C2F2-D0B7-2EAE467360A0">
<createdBy>jandrews1</createdBy>
<createdTime>2016-03-03 21:09:22 UTC</createdTime>
<ownerDesignName>SOLO_MEC_Tables_v1</ownerDesignName>
<schemaObject>E7FE513C-9018-FE2C-2B46-6C26966C9564</schemaObject>
<segment>B0C4B465-63AA-F59F-AF89-A38EA13C370E</segment>
<tableSpace>2D0C5141-F55A-D855-FEEF-15D238B39C97</tableSpace>
</IndexProxy>
</indexProxies>
<foreignKeys>
<ForeignKey class="oracle.dbtools.crest.model.design.storage.oracle.v10g.FKProxyOraclev10g" name="FK_MEC_ATTRIBUTE_VALUE1" id="EF15A3B8-9D28-60FB-2738-1E99F809A2D5">
<createdBy>jandrews1</createdBy>
<createdTime>2016-03-03 21:09:23 UTC</createdTime>
<ownerDesignName>SOLO_MEC_Tables_v1</ownerDesignName>
</ForeignKey>
</foreignKeys>
<primaryKeys>
<PrimaryKey class="oracle.dbtools.crest.model.design.storage.oracle.v10g.PKProxyOraclev10g" name="PK_MEC_ATTRIBUTE_VALUE" id="69002793-43CF-5EA1-3ABE-A2654535A23D">
<createdBy>jandrews1</createdBy>
<createdTime>2016-03-03 21:09:23 UTC</createdTime>
<ownerDesignName>SOLO_MEC_Tables_v1</ownerDesignName>
<segment>B0C4B465-63AA-F59F-AF89-A38EA13C370E</segment>
<tableSpace>2D0C5141-F55A-D855-FEEF-15D238B39C97</tableSpace>
<existingIndex>9AF008A8-8D02-C2F2-D0B7-2EAE467360A0</existingIndex>
<indexSegment>B0C4B465-63AA-F59F-AF89-A38EA13C370E</indexSegment>
<indexSort>SORTED</indexSort>
<usingIndex>BY INDEX NAME</usingIndex>
</PrimaryKey>
</primaryKeys>
</TableProxyOraclev11g>