<?xml version = '1.0' encoding = 'UTF-8'?>
<TableProxyOraclev11g class="oracle.dbtools.crest.model.design.storage.oracle.v11g.TableProxyOraclev11g" name="T_SPECIAL_REQUEST" directorySegmentName="seg_0" id="1A7EE6E9-CB36-1C48-88A6-B763EA57FA43">
<createdBy>jandrews1</createdBy>
<createdTime>2015-08-11 13:07:43 UTC</createdTime>
<ownerDesignName>SOLO_DECEMBER_RE</ownerDesignName>
<schemaObject>FA693F2C-EF1B-3E65-88D8-7194D19EDCEE</schemaObject>
<logging>YES</logging>
<partitionedRowMovement>DISABLE</partitionedRowMovement>
<segment>80EC53CE-933C-FDEB-394F-6D0FE206C597</segment>
<tableSpace>13A0D6EE-4ACF-AC9E-C994-1F7F5897441B</tableSpace>
<temporaryChanged>false</temporaryChanged>
<accessDriverType>oracle_loader</accessDriverType>
<rejectLimit></rejectLimit>
<columnProxies itemClass="oracle.dbtools.crest.model.design.storage.oracle.v12c.ColumnProxyOraclev12c">
<ColumnProxy name="BILL_START_DT" id="0990CCFB-65AA-0E9B-3191-2A57E8A8DF29">
<createdBy>jandrews1</createdBy>
<createdTime>2015-08-11 13:09:45 UTC</createdTime>
<ownerDesignName>SOLO_DECEMBER_RE</ownerDesignName>
</ColumnProxy>
<ColumnProxy name="REASON_CD" id="245CBA66-0ACA-2BF8-E242-8E86B4793FAE">
<createdBy>jandrews1</createdBy>
<createdTime>2015-08-11 13:09:45 UTC</createdTime>
<ownerDesignName>SOLO_DECEMBER_RE</ownerDesignName>
</ColumnProxy>
<ColumnProxy name="MODIFIED_BY" id="261AA72B-74DC-23F9-CB86-3CDA15785FB5">
<createdBy>jandrews1</createdBy>
<createdTime>2015-08-11 13:09:45 UTC</createdTime>
<ownerDesignName>SOLO_DECEMBER_RE</ownerDesignName>
</ColumnProxy>
<ColumnProxy name="CREATE_DTTM" id="2936B2AF-ECB3-13D7-020A-C99796A4F157">
<createdBy>jandrews1</createdBy>
<createdTime>2015-08-11 13:09:45 UTC</createdTime>
<ownerDesignName>SOLO_DECEMBER_RE</ownerDesignName>
</ColumnProxy>
<ColumnProxy name="BILL_STOP_DT" id="2CC36852-80DF-007E-CECB-D79D9097C65B">
<createdBy>jandrews1</createdBy>
<createdTime>2015-08-11 13:09:45 UTC</createdTime>
<ownerDesignName>SOLO_DECEMBER_RE</ownerDesignName>
</ColumnProxy>
<ColumnProxy name="RECORD_STAT" id="4005E68F-40F3-1F5D-E79B-56C9DFABF99F">
<createdBy>jandrews1</createdBy>
<createdTime>2015-08-11 13:09:45 UTC</createdTime>
<ownerDesignName>SOLO_DECEMBER_RE</ownerDesignName>
</ColumnProxy>
<ColumnProxy name="REQUESTED_COMPLETION_DT" id="4FF1ABAC-EB45-E024-ECF2-8CE08A98AD5E">
<createdBy>jandrews1</createdBy>
<createdTime>2015-08-11 13:09:45 UTC</createdTime>
<ownerDesignName>SOLO_DECEMBER_RE</ownerDesignName>
</ColumnProxy>
<ColumnProxy name="ACTUAL_COMPLETION_DTTM" id="75FBA8A8-8AF8-CBE9-6F6F-BBDD2B9335B7">
<createdBy>jandrews1</createdBy>
<createdTime>2015-08-11 13:09:45 UTC</createdTime>
<ownerDesignName>SOLO_DECEMBER_RE</ownerDesignName>
</ColumnProxy>
<ColumnProxy name="COMPLETION_CD" id="8E772C94-A26C-DE86-53D5-E099133ACC94">
<createdBy>jandrews1</createdBy>
<createdTime>2015-08-11 13:09:45 UTC</createdTime>
<ownerDesignName>SOLO_DECEMBER_RE</ownerDesignName>
</ColumnProxy>
<ColumnProxy name="SPECIAL_REQUEST_ID" id="A144BFC0-8BC7-D0BC-9F5A-2B61F84271F0">
<createdBy>jandrews1</createdBy>
<createdTime>2015-08-11 13:09:45 UTC</createdTime>
<ownerDesignName>SOLO_DECEMBER_RE</ownerDesignName>
</ColumnProxy>
<ColumnProxy name="CREATED_BY" id="AFD14647-D0D6-C0A5-51AC-DD71BD0FF13D">
<createdBy>jandrews1</createdBy>
<createdTime>2015-08-11 13:09:45 UTC</createdTime>
<ownerDesignName>SOLO_DECEMBER_RE</ownerDesignName>
</ColumnProxy>
<ColumnProxy name="CANCEL_CD" id="CD81E4DF-C6D8-91B9-72B3-C6875CEA6AB4">
<createdBy>jandrews1</createdBy>
<createdTime>2015-08-11 13:09:45 UTC</createdTime>
<ownerDesignName>SOLO_DECEMBER_RE</ownerDesignName>
</ColumnProxy>
<ColumnProxy name="SERVICE_ADDRESS_ID" id="D3951C24-75A8-9A4A-5272-BC95C14459E1">
<createdBy>jandrews1</createdBy>
<createdTime>2015-08-11 13:09:45 UTC</createdTime>
<ownerDesignName>SOLO_DECEMBER_RE</ownerDesignName>
</ColumnProxy>
<ColumnProxy name="DATA_SOURCE_TYPE_CD" id="D8E95055-7A7D-DBB5-307B-008BA3397EF4">
<createdBy>jandrews1</createdBy>
<createdTime>2015-08-11 13:09:45 UTC</createdTime>
<ownerDesignName>SOLO_DECEMBER_RE</ownerDesignName>
</ColumnProxy>
<ColumnProxy name="DNIS_CD" id="DC9422D9-DF0E-6F9D-84CC-5DEB9AD58909">
<createdBy>jandrews1</createdBy>
<createdTime>2015-08-11 13:09:45 UTC</createdTime>
<ownerDesignName>SOLO_DECEMBER_RE</ownerDesignName>
</ColumnProxy>
<ColumnProxy name="MODIFIED_DTTM" id="FA2E5433-C562-E3F8-9352-939B15F04BCD">
<createdBy>jandrews1</createdBy>
<createdTime>2015-08-11 13:09:45 UTC</createdTime>
<ownerDesignName>SOLO_DECEMBER_RE</ownerDesignName>
</ColumnProxy>
<ColumnProxy name="CREATED_DTTM" id="FEDFFFD1-A369-BEFE-3074-3153CCB54E0E">
<createdBy>jandrews1</createdBy>
<createdTime>2015-08-11 13:09:45 UTC</createdTime>
<ownerDesignName>SOLO_DECEMBER_RE</ownerDesignName>
</ColumnProxy>
</columnProxies>
<indexProxies>
<IndexProxy class="oracle.dbtools.crest.model.design.storage.oracle.v10g.IndexProxyOraclev10g" name="IDX_SPECIAL_REQUEST2" id="1A01233A-A991-8D27-852E-BF369656B979">
<createdBy>jandrews1</createdBy>
<createdTime>2015-08-11 13:10:45 UTC</createdTime>
<ownerDesignName>SOLO_DECEMBER_RE</ownerDesignName>
<schemaObject>FA693F2C-EF1B-3E65-88D8-7194D19EDCEE</schemaObject>
<segment>9D18D0B6-9321-F08C-FB12-13BF41CD9CF1</segment>
<tableSpace>51799F23-4FFD-4DE3-74FE-AAC19AE85DC0</tableSpace>
</IndexProxy>
<IndexProxy class="oracle.dbtools.crest.model.design.storage.oracle.v10g.IndexProxyOraclev10g" name="PK_SPECIAL_REQUEST" id="89C17BC5-02AC-636F-2116-7007D4D04437">
<createdBy>jandrews1</createdBy>
<createdTime>2015-08-11 13:10:45 UTC</createdTime>
<ownerDesignName>SOLO_DECEMBER_RE</ownerDesignName>
<schemaObject>FA693F2C-EF1B-3E65-88D8-7194D19EDCEE</schemaObject>
<segment>9D18D0B6-9321-F08C-FB12-13BF41CD9CF1</segment>
<tableSpace>51799F23-4FFD-4DE3-74FE-AAC19AE85DC0</tableSpace>
</IndexProxy>
<IndexProxy class="oracle.dbtools.crest.model.design.storage.oracle.v10g.IndexProxyOraclev10g" name="IDX_SPECIAL_REQUEST1" id="AE137F3D-E74A-EE42-E93F-83589D6D824C">
<createdBy>jandrews1</createdBy>
<createdTime>2015-08-11 13:10:45 UTC</createdTime>
<ownerDesignName>SOLO_DECEMBER_RE</ownerDesignName>
<schemaObject>FA693F2C-EF1B-3E65-88D8-7194D19EDCEE</schemaObject>
<segment>9D18D0B6-9321-F08C-FB12-13BF41CD9CF1</segment>
<tableSpace>51799F23-4FFD-4DE3-74FE-AAC19AE85DC0</tableSpace>
</IndexProxy>
</indexProxies>
<foreignKeys>
<ForeignKey class="oracle.dbtools.crest.model.design.storage.oracle.v10g.FKProxyOraclev10g" name="FK_SPECIAL_REQUEST1" id="37D50949-A51D-7642-856F-2CE64A2629F2">
<createdBy>jandrews1</createdBy>
<createdTime>2015-08-11 13:21:16 UTC</createdTime>
<ownerDesignName>SOLO_DECEMBER_RE</ownerDesignName>
</ForeignKey>
<ForeignKey class="oracle.dbtools.crest.model.design.storage.oracle.v10g.FKProxyOraclev10g" name="FK_SPECIAL_REQUEST2" id="70B62B04-38E9-EA14-B3B1-75D1A3B5D2A8">
<createdBy>jandrews1</createdBy>
<createdTime>2015-08-11 13:21:16 UTC</createdTime>
<ownerDesignName>SOLO_DECEMBER_RE</ownerDesignName>
</ForeignKey>
<ForeignKey class="oracle.dbtools.crest.model.design.storage.oracle.v10g.FKProxyOraclev10g" name="FK_SPECIAL_REQUEST" id="7B0E6C30-B979-122D-C139-25A3B52DF768">
<createdBy>jandrews1</createdBy>
<createdTime>2015-08-11 13:21:16 UTC</createdTime>
<ownerDesignName>SOLO_DECEMBER_RE</ownerDesignName>
</ForeignKey>
</foreignKeys>
<primaryKeys>
<PrimaryKey class="oracle.dbtools.crest.model.design.storage.oracle.v10g.PKProxyOraclev10g" name="PK_SPECIAL_REQUEST" id="FD3E27A3-2758-C7BA-74A3-B301E0E7D4BB">
<createdBy>jandrews1</createdBy>
<createdTime>2015-08-11 13:12:46 UTC</createdTime>
<ownerDesignName>SOLO_DECEMBER_RE</ownerDesignName>
<segment>9D18D0B6-9321-F08C-FB12-13BF41CD9CF1</segment>
<tableSpace>51799F23-4FFD-4DE3-74FE-AAC19AE85DC0</tableSpace>
<existingIndex>89C17BC5-02AC-636F-2116-7007D4D04437</existingIndex>
<indexSegment>9D18D0B6-9321-F08C-FB12-13BF41CD9CF1</indexSegment>
<indexSort>SORTED</indexSort>
<usingIndex>BY INDEX NAME</usingIndex>
</PrimaryKey>
</primaryKeys>
</TableProxyOraclev11g>