<?xml version = '1.0' encoding = 'UTF-8'?>
<Relation class="oracle.dbtools.crest.model.design.logical.Relation" name="FK_EQUIP_INSTANCE_STATUS2" directorySegmentName="seg_3" id="0BF4C9A4-B26D-6FC4-D87F-1B638D6CE784">
<createdBy>jandrews1</createdBy>
<createdTime>2015-12-17 14:33:30 UTC</createdTime>
<generatorID>4C3271F8-1FA6-9262-2BF5-B58CD94B3335</generatorID>
<ownerDesignName>SOLO_DECEMBER_RE</ownerDesignName>
<engineerTo>
<item key="F751E03D-C8A7-4CF2-7EA7-CC30B209F748" value="true"/>
</engineerTo>
<sourcePk>CC2A63DD-BAAD-6560-D174-F095F1FE170B</sourcePk>
<dominantRole>A7B3AA68-9C1D-7DE9-4377-D8493B9DC30F</dominantRole>
<identifying>true</identifying>
<optionalSource>true</optionalSource>
<optionalTarget>false</optionalTarget>
<sourceCardinality>1</sourceCardinality>
<sourceEntity>A7B3AA68-9C1D-7DE9-4377-D8493B9DC30F</sourceEntity>
<targetCardinalityString>1</targetCardinalityString>
<targetEntity>A94C10F8-A3B1-0011-F51D-D4FE9B3AE936</targetEntity>
<transferable>true</transferable>
<deleteRule>NO ACTION</deleteRule>
</Relation>