<?xml version = '1.0' encoding = 'UTF-8'?>
<FKIndexAssociation class="oracle.dbtools.crest.model.design.relational.FKIndexAssociation" directorySegmentName="seg_2" id="A6FC43D5-B645-5ABA-76BE-680700362CF2" containerWithKeyObject="DD1DD5A4-29E6-7E36-3C4B-2728B6A6E774" localFKIndex="8E481586-F27D-1E4E-53DF-3026F91EF571" name="FK_CONTROLLER1">
<sourceConnName>SOLO_Prod</sourceConnName>
<sourceObjSchema>CHTR</sourceObjSchema>
<sourceObjName>FK_CONTROLLER1</sourceObjName>
<createdBy>jandrews1</createdBy>
<createdTime>2015-08-11 13:21:16 UTC</createdTime>
<ownerDesignName>SOLO_DECEMBER_RE</ownerDesignName>
<deleteRule>NO ACTION</deleteRule>
<referredTableID>67590E7C-5311-3385-0539-7EB7CAC5EF18</referredTableID>
<keyObject>5CF5E21D-B1B0-8A6A-FFCA-42EF290E283A</keyObject>
<referredKeyID>5CF5E21D-B1B0-8A6A-FFCA-42EF290E283A</referredKeyID>
<mandatory>false</mandatory>
<transferable>true</transferable>
<rely>false</rely>
<columnDependencyConstraintGenerateInDDL>true</columnDependencyConstraintGenerateInDDL>
</FKIndexAssociation>